{
  "version": 3,
  "responderUsername": "",
  "initialLocation": "panel",
  "requests": [],
  "sessionId": "ac3d6099-bad4-4998-b989-b9107f7687c9",
  "creationDate": 1767130844612,
  "lastMessageDate": 1767130844612,
  "hasPendingEdits": false,
  "contrib": {
    "chatDynamicVariableModel": []
  },
  "attachments": [],
  "mode": {
    "id": "agent",
    "kind": "agent"
  },
  "inputText": "",
  "selections": [
    {
      "startLineNumber": 1,
      "startColumn": 1,
      "endLineNumber": 1,
      "endColumn": 1,
      "selectionStartLineNumber": 1,
      "selectionStartColumn": 1,
      "positionLineNumber": 1,
      "positionColumn": 1
    }
  ]
}